{
  "transferencias": [
    {
      "id": "1",
      "valor": 35,
      "destino": "1212-1",
      "data": "2020-11-04T16:30:10.710Z"
    },
    {
      "id": "2",
      "valor": 40,
      "destino": "1213-1",
      "data": "2020-11-04T21:24:10.710Z"
    },
    {
      "id": "3",
      "valor": 12.5,
      "destino": "1214-1",
      "data": "2020-11-05T21:14:10.710Z"
    },
    {
      "valor": 100,
      "destino": "1234-1",
      "data": "2022-08-17T14:46:57.130Z",
      "id": "xJpgkEo"
    },
    {
      "valor": 30,
      "destino": "1011-4",
      "data": "2022-08-17T17:06:36.011Z",
      "id": "gdDycBC"
    },
    {
      "valor": 2000,
      "destino": " 1010-2",
      "data": "2022-08-17T17:13:07.156Z",
      "id": "widZpoG"
    },
    {
      "valor": 200,
      "destino": "1010-2",
      "data": "2022-11-17T14:32:13.470Z",
      "id": "HyCKicN"
    }
  ]
}